affinidi_tdk_auth_provider/__init__.py
affinidi_tdk_auth_provider/py.typed
affinidi_tdk_auth_provider/_jsii/__init__.py
affinidi_tdk_auth_provider/_jsii/auth-provider@1.33.3.jsii.tgz
affinidi_tdk_auth_provider-1.33.3.dist-info/LICENSE
affinidi_tdk_auth_provider-1.33.3.dist-info/METADATA
affinidi_tdk_auth_provider-1.33.3.dist-info/WHEEL
affinidi_tdk_auth_provider-1.33.3.dist-info/top_level.txt
affinidi_tdk_auth_provider-1.33.3.dist-info/RECORD
