Metadata-Version: 2.1
Name: affinidi_tdk_auth_provider
Version: 1.33.3
Summary: Internal module for managing access tokens
Home-page: https://github.com/affinidi/affinidi-tdk#readme
Author: Affinidi
License: Apache-2.0
Project-URL: Source, https://github.com/affinidi/affinidi-tdk
Classifier: Intended Audience :: Developers
Classifier: Operating System :: OS Independent
Classifier: Programming Language :: JavaScript
Classifier: Programming Language :: Python :: 3 :: Only
Classifier: Programming Language :: Python :: 3.9
Classifier: Programming Language :: Python :: 3.10
Classifier: Programming Language :: Python :: 3.11
Classifier: Typing :: Typed
Classifier: Development Status :: 5 - Production/Stable
Classifier: License :: OSI Approved
Requires-Python: ~=3.9
License-File: LICENSE
Requires-Dist: jsii<2.0.0,>=1.112.0
Requires-Dist: publication>=0.0.3
Requires-Dist: typeguard<4.3.0,>=2.13.3
